syngular/__init__.py
syngular/field.py
syngular/ideal.py
syngular/ideal_algorithms.py
syngular/monomial.py
syngular/point.py
syngular/polynomial.py
syngular/qring.py
syngular/ring.py
syngular/settings.py
syngular/tools.py
syngular/variety.py
syngular/version.py
syngular-0.5.1.dist-info/LICENSE.txt
syngular-0.5.1.dist-info/METADATA
syngular-0.5.1.dist-info/WHEEL
syngular-0.5.1.dist-info/top_level.txt
syngular-0.5.1.dist-info/RECORD
