Metadata-Version: 2.1
Name: syngular
Version: 0.5.1
Summary: An Object-Oriented Python Interface and Extension to Singular
Home-page: https://github.com/GDeLaurentis/syngular
Download-URL: https://github.com/GDeLaurentis/syngular/archive/0.5.1.tar.gz
Author: Giuseppe De Laurentis
Author-email: g.dl@hotmail.it
License: GNU General Public License v3.0
Project-URL: Documentation, https://gdelaurentis.github.io/syngular/
Project-URL: Issues, https://github.com/GDeLaurentis/syngular/issues
Keywords: syngular,singular,algebraic geometry,ring,ideal,polynomials,polynomial equations
Classifier: Development Status :: 4 - Beta
Classifier: Intended Audience :: Science/Research
Classifier: Topic :: Scientific/Engineering :: Physics
Classifier: License :: OSI Approved :: GNU General Public License v3 (GPLv3)
Classifier: Programming Language :: Python :: 3.9
Classifier: Programming Language :: Python :: 3.10
Classifier: Programming Language :: Python :: 3.11
Classifier: Programming Language :: Python :: 3.12
Classifier: Programming Language :: Python :: 3.13
License-File: LICENSE.txt
Requires-Dist: multiset
Requires-Dist: numpy
Requires-Dist: pyadic
Requires-Dist: sympy
